odoo8_addon_l10n_it_fatturapa_out_triple_discount-8.0.2.0.0-nspkg.pth
odoo_addons/l10n_it_fatturapa_out_triple_discount/README.rst
odoo_addons/l10n_it_fatturapa_out_triple_discount/__init__.py
odoo_addons/l10n_it_fatturapa_out_triple_discount/__openerp__.py
odoo_addons/l10n_it_fatturapa_out_triple_discount/i18n/l10n_it_fatturapa_out_triple_discount.pot
odoo_addons/l10n_it_fatturapa_out_triple_discount/readme/CONTRIBUTORS.rst
odoo_addons/l10n_it_fatturapa_out_triple_discount/readme/DESCRIPTION.rst
odoo_addons/l10n_it_fatturapa_out_triple_discount/static/description/icon.png
odoo_addons/l10n_it_fatturapa_out_triple_discount/static/description/index.html
odoo_addons/l10n_it_fatturapa_out_triple_discount/tests/__init__.py
odoo_addons/l10n_it_fatturapa_out_triple_discount/tests/test_fatturapa_triple_discount.py
odoo_addons/l10n_it_fatturapa_out_triple_discount/tests/data/IT06363391001_00001.xml
odoo_addons/l10n_it_fatturapa_out_triple_discount/wizard/__init__.py
odoo_addons/l10n_it_fatturapa_out_triple_discount/wizard/wizard_export_fatturapa.py
odoo8_addon_l10n_it_fatturapa_out_triple_discount-8.0.2.0.0.dist-info/METADATA
odoo8_addon_l10n_it_fatturapa_out_triple_discount-8.0.2.0.0.dist-info/WHEEL
odoo8_addon_l10n_it_fatturapa_out_triple_discount-8.0.2.0.0.dist-info/namespace_packages.txt
odoo8_addon_l10n_it_fatturapa_out_triple_discount-8.0.2.0.0.dist-info/top_level.txt
odoo8_addon_l10n_it_fatturapa_out_triple_discount-8.0.2.0.0.dist-info/RECORD
